{"nodes": [{"id": "c_laragon_www_catatan_vendor_codeigniter4_shield_docs_customization_route_config_md", "label": "route_config.md", "file_type": "document", "source_file": "C:\\laragon\\www\\catatan\\vendor\\codeigniter4\\shield\\docs\\customization\\route_config.md", "source_location": "L1"}, {"id": "customization_route_config_customizing_routes", "label": "Customizing Routes", "file_type": "document", "source_file": "C:\\laragon\\www\\catatan\\vendor\\codeigniter4\\shield\\docs\\customization\\route_config.md", "source_location": "L1"}, {"id": "customization_route_config_change_some_routes", "label": "Change Some Routes", "file_type": "document", "source_file": "C:\\laragon\\www\\catatan\\vendor\\codeigniter4\\shield\\docs\\customization\\route_config.md", "source_location": "L3"}, {"id": "customization_route_config_codeblock_1", "label": "code:php (service('auth')->routes($routes, ['except' => ['login', 'reg)", "file_type": "document", "source_file": "C:\\laragon\\www\\catatan\\vendor\\codeigniter4\\shield\\docs\\customization\\route_config.md", "source_location": "L9"}, {"id": "customization_route_config_codeblock_2", "label": "code:php ($routes->get('login', '\\App\\Controllers\\Auth\\LoginController)", "file_type": "document", "source_file": "C:\\laragon\\www\\catatan\\vendor\\codeigniter4\\shield\\docs\\customization\\route_config.md", "source_location": "L15"}, {"id": "customization_route_config_change_namespace", "label": "Change Namespace", "file_type": "document", "source_file": "C:\\laragon\\www\\catatan\\vendor\\codeigniter4\\shield\\docs\\customization\\route_config.md", "source_location": "L22"}, {"id": "customization_route_config_codeblock_3", "label": "code:php (service('auth')->routes($routes, ['namespace' => '\\App\\Contr)", "file_type": "document", "source_file": "C:\\laragon\\www\\catatan\\vendor\\codeigniter4\\shield\\docs\\customization\\route_config.md", "source_location": "L26"}, {"id": "customization_route_config_use_locale_routes", "label": "Use Locale Routes", "file_type": "document", "source_file": "C:\\laragon\\www\\catatan\\vendor\\codeigniter4\\shield\\docs\\customization\\route_config.md", "source_location": "L32"}, {"id": "customization_route_config_codeblock_4", "label": "code:php ($routes->group('{locale}', static function($routes) {)", "file_type": "document", "source_file": "C:\\laragon\\www\\catatan\\vendor\\codeigniter4\\shield\\docs\\customization\\route_config.md", "source_location": "L37"}, {"id": "customization_route_config_codeblock_5", "label": "code:text (+--------+----------------------------------+---------------)", "file_type": "document", "source_file": "C:\\laragon\\www\\catatan\\vendor\\codeigniter4\\shield\\docs\\customization\\route_config.md", "source_location": "L45"}, {"id": "customization_route_config_codeblock_6", "label": "code:php (public $globals = [)", "file_type": "document", "source_file": "C:\\laragon\\www\\catatan\\vendor\\codeigniter4\\shield\\docs\\customization\\route_config.md", "source_location": "L66"}], "edges": [{"source": "c_laragon_www_catatan_vendor_codeigniter4_shield_docs_customization_route_config_md", "target": "customization_route_config_customizing_routes", "relation": "contains", "confidence": "EXTRACTED", "source_file": "C:\\laragon\\www\\catatan\\vendor\\codeigniter4\\shield\\docs\\customization\\route_config.md", "source_location": "L1", "weight": 1.0}, {"source": "customization_route_config_customizing_routes", "target": "customization_route_config_change_some_routes", "relation": "contains", "confidence": "EXTRACTED", "source_file": "C:\\laragon\\www\\catatan\\vendor\\codeigniter4\\shield\\docs\\customization\\route_config.md", "source_location": "L3", "weight": 1.0}, {"source": "customization_route_config_change_some_routes", "target": "customization_route_config_codeblock_1", "relation": "contains", "confidence": "EXTRACTED", "source_file": "C:\\laragon\\www\\catatan\\vendor\\codeigniter4\\shield\\docs\\customization\\route_config.md", "source_location": "L9", "weight": 1.0}, {"source": "customization_route_config_change_some_routes", "target": "customization_route_config_codeblock_2", "relation": "contains", "confidence": "EXTRACTED", "source_file": "C:\\laragon\\www\\catatan\\vendor\\codeigniter4\\shield\\docs\\customization\\route_config.md", "source_location": "L15", "weight": 1.0}, {"source": "customization_route_config_customizing_routes", "target": "customization_route_config_change_namespace", "relation": "contains", "confidence": "EXTRACTED", "source_file": "C:\\laragon\\www\\catatan\\vendor\\codeigniter4\\shield\\docs\\customization\\route_config.md", "source_location": "L22", "weight": 1.0}, {"source": "customization_route_config_change_namespace", "target": "customization_route_config_codeblock_3", "relation": "contains", "confidence": "EXTRACTED", "source_file": "C:\\laragon\\www\\catatan\\vendor\\codeigniter4\\shield\\docs\\customization\\route_config.md", "source_location": "L26", "weight": 1.0}, {"source": "customization_route_config_customizing_routes", "target": "customization_route_config_use_locale_routes", "relation": "contains", "confidence": "EXTRACTED", "source_file": "C:\\laragon\\www\\catatan\\vendor\\codeigniter4\\shield\\docs\\customization\\route_config.md", "source_location": "L32", "weight": 1.0}, {"source": "customization_route_config_use_locale_routes", "target": "customization_route_config_codeblock_4", "relation": "contains", "confidence": "EXTRACTED", "source_file": "C:\\laragon\\www\\catatan\\vendor\\codeigniter4\\shield\\docs\\customization\\route_config.md", "source_location": "L37", "weight": 1.0}, {"source": "customization_route_config_use_locale_routes", "target": "customization_route_config_codeblock_5", "relation": "contains", "confidence": "EXTRACTED", "source_file": "C:\\laragon\\www\\catatan\\vendor\\codeigniter4\\shield\\docs\\customization\\route_config.md", "source_location": "L45", "weight": 1.0}, {"source": "customization_route_config_use_locale_routes", "target": "customization_route_config_codeblock_6", "relation": "contains", "confidence": "EXTRACTED", "source_file": "C:\\laragon\\www\\catatan\\vendor\\codeigniter4\\shield\\docs\\customization\\route_config.md", "source_location": "L66", "weight": 1.0}], "input_tokens": 0, "output_tokens": 0}