{"nodes": [{"id": "c_laragon_www_catatan_vendor_codeigniter4_shield_docs_getting_started_authenticators_md", "label": "authenticators.md", "file_type": "document", "source_file": "C:\\laragon\\www\\catatan\\vendor\\codeigniter4\\shield\\docs\\getting_started\\authenticators.md", "source_location": "L1"}, {"id": "getting_started_authenticators_authenticators", "label": "Authenticators", "file_type": "document", "source_file": "C:\\laragon\\www\\catatan\\vendor\\codeigniter4\\shield\\docs\\getting_started\\authenticators.md", "source_location": "L1"}, {"id": "getting_started_authenticators_authenticator_list", "label": "Authenticator List", "file_type": "document", "source_file": "C:\\laragon\\www\\catatan\\vendor\\codeigniter4\\shield\\docs\\getting_started\\authenticators.md", "source_location": "L3"}], "edges": [{"source": "c_laragon_www_catatan_vendor_codeigniter4_shield_docs_getting_started_authenticators_md", "target": "getting_started_authenticators_authenticators", "relation": "contains", "confidence": "EXTRACTED", "source_file": "C:\\laragon\\www\\catatan\\vendor\\codeigniter4\\shield\\docs\\getting_started\\authenticators.md", "source_location": "L1", "weight": 1.0}, {"source": "getting_started_authenticators_authenticators", "target": "getting_started_authenticators_authenticator_list", "relation": "contains", "confidence": "EXTRACTED", "source_file": "C:\\laragon\\www\\catatan\\vendor\\codeigniter4\\shield\\docs\\getting_started\\authenticators.md", "source_location": "L3", "weight": 1.0}], "input_tokens": 0, "output_tokens": 0}