{"nodes": [{"id": "c_laragon_www_catatan_vendor_codeigniter4_framework_system_exceptions_frameworkexception_php", "label": "FrameworkException.php", "file_type": "code", "source_file": "C:\\laragon\\www\\catatan\\vendor\\codeigniter4\\framework\\system\\Exceptions\\FrameworkException.php", "source_location": "L1"}, {"id": "exceptions_frameworkexception_frameworkexception", "label": "FrameworkException", "file_type": "code", "source_file": "C:\\laragon\\www\\catatan\\vendor\\codeigniter4\\framework\\system\\Exceptions\\FrameworkException.php", "source_location": "L22"}, {"id": "exceptions_frameworkexception_frameworkexception_forenabledzliboutputcompression", "label": ".forEnabledZlibOutputCompression()", "file_type": "code", "source_file": "C:\\laragon\\www\\catatan\\vendor\\codeigniter4\\framework\\system\\Exceptions\\FrameworkException.php", "source_location": "L29"}, {"id": "exceptions_frameworkexception_frameworkexception_forinvalidfile", "label": ".forInvalidFile()", "file_type": "code", "source_file": "C:\\laragon\\www\\catatan\\vendor\\codeigniter4\\framework\\system\\Exceptions\\FrameworkException.php", "source_location": "L37"}, {"id": "exceptions_frameworkexception_frameworkexception_forinvaliddirectory", "label": ".forInvalidDirectory()", "file_type": "code", "source_file": "C:\\laragon\\www\\catatan\\vendor\\codeigniter4\\framework\\system\\Exceptions\\FrameworkException.php", "source_location": "L45"}, {"id": "exceptions_frameworkexception_frameworkexception_forcopyerror", "label": ".forCopyError()", "file_type": "code", "source_file": "C:\\laragon\\www\\catatan\\vendor\\codeigniter4\\framework\\system\\Exceptions\\FrameworkException.php", "source_location": "L53"}, {"id": "exceptions_frameworkexception_frameworkexception_formissingextension", "label": ".forMissingExtension()", "file_type": "code", "source_file": "C:\\laragon\\www\\catatan\\vendor\\codeigniter4\\framework\\system\\Exceptions\\FrameworkException.php", "source_location": "L63"}, {"id": "exceptions_frameworkexception_frameworkexception_fornohandlers", "label": ".forNoHandlers()", "file_type": "code", "source_file": "C:\\laragon\\www\\catatan\\vendor\\codeigniter4\\framework\\system\\Exceptions\\FrameworkException.php", "source_location": "L82"}, {"id": "exceptions_frameworkexception_frameworkexception_forfabricatorcreatefailed", "label": ".forFabricatorCreateFailed()", "file_type": "code", "source_file": "C:\\laragon\\www\\catatan\\vendor\\codeigniter4\\framework\\system\\Exceptions\\FrameworkException.php", "source_location": "L90"}], "edges": [{"source": "c_laragon_www_catatan_vendor_codeigniter4_framework_system_exceptions_frameworkexception_php", "target": "exceptions_frameworkexception_frameworkexception", "relation": "contains", "confidence": "EXTRACTED", "source_file": "C:\\laragon\\www\\catatan\\vendor\\codeigniter4\\framework\\system\\Exceptions\\FrameworkException.php", "source_location": "L22", "weight": 1.0}, {"source": "exceptions_frameworkexception_frameworkexception", "target": "exceptions_frameworkexception_frameworkexception_forenabledzliboutputcompression", "relation": "method", "confidence": "EXTRACTED", "source_file": "C:\\laragon\\www\\catatan\\vendor\\codeigniter4\\framework\\system\\Exceptions\\FrameworkException.php", "source_location": "L29", "weight": 1.0}, {"source": "exceptions_frameworkexception_frameworkexception", "target": "exceptions_frameworkexception_frameworkexception_forinvalidfile", "relation": "method", "confidence": "EXTRACTED", "source_file": "C:\\laragon\\www\\catatan\\vendor\\codeigniter4\\framework\\system\\Exceptions\\FrameworkException.php", "source_location": "L37", "weight": 1.0}, {"source": "exceptions_frameworkexception_frameworkexception", "target": "exceptions_frameworkexception_frameworkexception_forinvaliddirectory", "relation": "method", "confidence": "EXTRACTED", "source_file": "C:\\laragon\\www\\catatan\\vendor\\codeigniter4\\framework\\system\\Exceptions\\FrameworkException.php", "source_location": "L45", "weight": 1.0}, {"source": "exceptions_frameworkexception_frameworkexception", "target": "exceptions_frameworkexception_frameworkexception_forcopyerror", "relation": "method", "confidence": "EXTRACTED", "source_file": "C:\\laragon\\www\\catatan\\vendor\\codeigniter4\\framework\\system\\Exceptions\\FrameworkException.php", "source_location": "L53", "weight": 1.0}, {"source": "exceptions_frameworkexception_frameworkexception", "target": "exceptions_frameworkexception_frameworkexception_formissingextension", "relation": "method", "confidence": "EXTRACTED", "source_file": "C:\\laragon\\www\\catatan\\vendor\\codeigniter4\\framework\\system\\Exceptions\\FrameworkException.php", "source_location": "L63", "weight": 1.0}, {"source": "exceptions_frameworkexception_frameworkexception", "target": "exceptions_frameworkexception_frameworkexception_fornohandlers", "relation": "method", "confidence": "EXTRACTED", "source_file": "C:\\laragon\\www\\catatan\\vendor\\codeigniter4\\framework\\system\\Exceptions\\FrameworkException.php", "source_location": "L82", "weight": 1.0}, {"source": "exceptions_frameworkexception_frameworkexception", "target": "exceptions_frameworkexception_frameworkexception_forfabricatorcreatefailed", "relation": "method", "confidence": "EXTRACTED", "source_file": "C:\\laragon\\www\\catatan\\vendor\\codeigniter4\\framework\\system\\Exceptions\\FrameworkException.php", "source_location": "L90", "weight": 1.0}], "raw_calls": [{"caller_nid": "exceptions_frameworkexception_frameworkexception_forenabledzliboutputcompression", "callee": "lang", "is_member_call": false, "source_file": "C:\\laragon\\www\\catatan\\vendor\\codeigniter4\\framework\\system\\Exceptions\\FrameworkException.php", "source_location": "L31"}, {"caller_nid": "exceptions_frameworkexception_frameworkexception_forinvalidfile", "callee": "lang", "is_member_call": false, "source_file": "C:\\laragon\\www\\catatan\\vendor\\codeigniter4\\framework\\system\\Exceptions\\FrameworkException.php", "source_location": "L39"}, {"caller_nid": "exceptions_frameworkexception_frameworkexception_forinvaliddirectory", "callee": "lang", "is_member_call": false, "source_file": "C:\\laragon\\www\\catatan\\vendor\\codeigniter4\\framework\\system\\Exceptions\\FrameworkException.php", "source_location": "L47"}, {"caller_nid": "exceptions_frameworkexception_frameworkexception_forcopyerror", "callee": "lang", "is_member_call": false, "source_file": "C:\\laragon\\www\\catatan\\vendor\\codeigniter4\\framework\\system\\Exceptions\\FrameworkException.php", "source_location": "L55"}, {"caller_nid": "exceptions_frameworkexception_frameworkexception_formissingextension", "callee": "str_contains", "is_member_call": false, "source_file": "C:\\laragon\\www\\catatan\\vendor\\codeigniter4\\framework\\system\\Exceptions\\FrameworkException.php", "source_location": "L65"}, {"caller_nid": "exceptions_frameworkexception_frameworkexception_formissingextension", "callee": "sprintf", "is_member_call": false, "source_file": "C:\\laragon\\www\\catatan\\vendor\\codeigniter4\\framework\\system\\Exceptions\\FrameworkException.php", "source_location": "L67"}, {"caller_nid": "exceptions_frameworkexception_frameworkexception_formissingextension", "callee": "lang", "is_member_call": false, "source_file": "C:\\laragon\\www\\catatan\\vendor\\codeigniter4\\framework\\system\\Exceptions\\FrameworkException.php", "source_location": "L73"}, {"caller_nid": "exceptions_frameworkexception_frameworkexception_fornohandlers", "callee": "lang", "is_member_call": false, "source_file": "C:\\laragon\\www\\catatan\\vendor\\codeigniter4\\framework\\system\\Exceptions\\FrameworkException.php", "source_location": "L84"}, {"caller_nid": "exceptions_frameworkexception_frameworkexception_forfabricatorcreatefailed", "callee": "lang", "is_member_call": false, "source_file": "C:\\laragon\\www\\catatan\\vendor\\codeigniter4\\framework\\system\\Exceptions\\FrameworkException.php", "source_location": "L92"}]}