{"nodes": [{"id": "c_laragon_www_catatan_vendor_codeigniter4_framework_system_router_autorouter_php", "label": "AutoRouter.php", "file_type": "code", "source_file": "C:\\laragon\\www\\catatan\\vendor\\codeigniter4\\framework\\system\\Router\\AutoRouter.php", "source_location": "L1"}, {"id": "router_autorouter_autorouter", "label": "AutoRouter", "file_type": "code", "source_file": "C:\\laragon\\www\\catatan\\vendor\\codeigniter4\\framework\\system\\Router\\AutoRouter.php", "source_location": "L23"}, {"id": "router_autorouter_autorouter_construct", "label": ".__construct()", "file_type": "code", "source_file": "C:\\laragon\\www\\catatan\\vendor\\codeigniter4\\framework\\system\\Router\\AutoRouter.php", "source_location": "L31"}, {"id": "router_autorouter_autorouter_getroute", "label": ".getRoute()", "file_type": "code", "source_file": "C:\\laragon\\www\\catatan\\vendor\\codeigniter4\\framework\\system\\Router\\AutoRouter.php", "source_location": "L66"}, {"id": "router_autorouter_autorouter_settranslateuridashes", "label": ".setTranslateURIDashes()", "file_type": "code", "source_file": "C:\\laragon\\www\\catatan\\vendor\\codeigniter4\\framework\\system\\Router\\AutoRouter.php", "source_location": "L171"}, {"id": "router_autorouter_autorouter_scancontrollers", "label": ".scanControllers()", "file_type": "code", "source_file": "C:\\laragon\\www\\catatan\\vendor\\codeigniter4\\framework\\system\\Router\\AutoRouter.php", "source_location": "L185"}, {"id": "router_autorouter_autorouter_isvalidsegment", "label": ".isValidSegment()", "file_type": "code", "source_file": "C:\\laragon\\www\\catatan\\vendor\\codeigniter4\\framework\\system\\Router\\AutoRouter.php", "source_location": "L231"}, {"id": "router_autorouter_autorouter_setdirectory", "label": ".setDirectory()", "file_type": "code", "source_file": "C:\\laragon\\www\\catatan\\vendor\\codeigniter4\\framework\\system\\Router\\AutoRouter.php", "source_location": "L245"}, {"id": "router_autorouter_autorouter_directory", "label": ".directory()", "file_type": "code", "source_file": "C:\\laragon\\www\\catatan\\vendor\\codeigniter4\\framework\\system\\Router\\AutoRouter.php", "source_location": "L276"}, {"id": "router_autorouter_autorouter_controllername", "label": ".controllerName()", "file_type": "code", "source_file": "C:\\laragon\\www\\catatan\\vendor\\codeigniter4\\framework\\system\\Router\\AutoRouter.php", "source_location": "L281"}, {"id": "router_autorouter_autorouter_methodname", "label": ".methodName()", "file_type": "code", "source_file": "C:\\laragon\\www\\catatan\\vendor\\codeigniter4\\framework\\system\\Router\\AutoRouter.php", "source_location": "L288"}], "edges": [{"source": "c_laragon_www_catatan_vendor_codeigniter4_framework_system_router_autorouter_php", "target": "closure", "relation": "imports", "context": "import", "confidence": "EXTRACTED", "source_file": "C:\\laragon\\www\\catatan\\vendor\\codeigniter4\\framework\\system\\Router\\AutoRouter.php", "source_location": "L16", "weight": 1.0}, {"source": "c_laragon_www_catatan_vendor_codeigniter4_framework_system_router_autorouter_php", "target": "pagenotfoundexception", "relation": "imports", "context": "import", "confidence": "EXTRACTED", "source_file": "C:\\laragon\\www\\catatan\\vendor\\codeigniter4\\framework\\system\\Router\\AutoRouter.php", "source_location": "L17", "weight": 1.0}, {"source": "c_laragon_www_catatan_vendor_codeigniter4_framework_system_router_autorouter_php", "target": "responseinterface", "relation": "imports", "context": "import", "confidence": "EXTRACTED", "source_file": "C:\\laragon\\www\\catatan\\vendor\\codeigniter4\\framework\\system\\Router\\AutoRouter.php", "source_location": "L18", "weight": 1.0}, {"source": "c_laragon_www_catatan_vendor_codeigniter4_framework_system_router_autorouter_php", "target": "router_autorouter_autorouter", "relation": "contains", "confidence": "EXTRACTED", "source_file": "C:\\laragon\\www\\catatan\\vendor\\codeigniter4\\framework\\system\\Router\\AutoRouter.php", "source_location": "L23", "weight": 1.0}, {"source": "router_autorouter_autorouter", "target": "router_autorouter_autorouter_construct", "relation": "method", "confidence": "EXTRACTED", "source_file": "C:\\laragon\\www\\catatan\\vendor\\codeigniter4\\framework\\system\\Router\\AutoRouter.php", "source_location": "L31", "weight": 1.0}, {"source": "router_autorouter_autorouter", "target": "router_autorouter_autorouter_getroute", "relation": "method", "confidence": "EXTRACTED", "source_file": "C:\\laragon\\www\\catatan\\vendor\\codeigniter4\\framework\\system\\Router\\AutoRouter.php", "source_location": "L66", "weight": 1.0}, {"source": "router_autorouter_autorouter", "target": "router_autorouter_autorouter_settranslateuridashes", "relation": "method", "confidence": "EXTRACTED", "source_file": "C:\\laragon\\www\\catatan\\vendor\\codeigniter4\\framework\\system\\Router\\AutoRouter.php", "source_location": "L171", "weight": 1.0}, {"source": "router_autorouter_autorouter", "target": "router_autorouter_autorouter_scancontrollers", "relation": "method", "confidence": "EXTRACTED", "source_file": "C:\\laragon\\www\\catatan\\vendor\\codeigniter4\\framework\\system\\Router\\AutoRouter.php", "source_location": "L185", "weight": 1.0}, {"source": "router_autorouter_autorouter", "target": "router_autorouter_autorouter_isvalidsegment", "relation": "method", "confidence": "EXTRACTED", "source_file": "C:\\laragon\\www\\catatan\\vendor\\codeigniter4\\framework\\system\\Router\\AutoRouter.php", "source_location": "L231", "weight": 1.0}, {"source": "router_autorouter_autorouter", "target": "router_autorouter_autorouter_setdirectory", "relation": "method", "confidence": "EXTRACTED", "source_file": "C:\\laragon\\www\\catatan\\vendor\\codeigniter4\\framework\\system\\Router\\AutoRouter.php", "source_location": "L245", "weight": 1.0}, {"source": "router_autorouter_autorouter", "target": "router_autorouter_autorouter_directory", "relation": "method", "confidence": "EXTRACTED", "source_file": "C:\\laragon\\www\\catatan\\vendor\\codeigniter4\\framework\\system\\Router\\AutoRouter.php", "source_location": "L276", "weight": 1.0}, {"source": "router_autorouter_autorouter", "target": "router_autorouter_autorouter_controllername", "relation": "method", "confidence": "EXTRACTED", "source_file": "C:\\laragon\\www\\catatan\\vendor\\codeigniter4\\framework\\system\\Router\\AutoRouter.php", "source_location": "L281", "weight": 1.0}, {"source": "router_autorouter_autorouter", "target": "router_autorouter_autorouter_methodname", "relation": "method", "confidence": "EXTRACTED", "source_file": "C:\\laragon\\www\\catatan\\vendor\\codeigniter4\\framework\\system\\Router\\AutoRouter.php", "source_location": "L288", "weight": 1.0}, {"source": "router_autorouter_autorouter_getroute", "target": "router_autorouter_autorouter_scancontrollers", "relation": "calls", "context": "call", "confidence": "EXTRACTED", "source_file": "C:\\laragon\\www\\catatan\\vendor\\codeigniter4\\framework\\system\\Router\\AutoRouter.php", "source_location": "L71", "weight": 1.0}, {"source": "router_autorouter_autorouter_getroute", "target": "router_autorouter_autorouter_controllername", "relation": "calls", "context": "call", "confidence": "EXTRACTED", "source_file": "C:\\laragon\\www\\catatan\\vendor\\codeigniter4\\framework\\system\\Router\\AutoRouter.php", "source_location": "L79", "weight": 1.0}, {"source": "router_autorouter_autorouter_getroute", "target": "router_autorouter_autorouter_isvalidsegment", "relation": "calls", "context": "call", "confidence": "EXTRACTED", "source_file": "C:\\laragon\\www\\catatan\\vendor\\codeigniter4\\framework\\system\\Router\\AutoRouter.php", "source_location": "L81", "weight": 1.0}, {"source": "router_autorouter_autorouter_getroute", "target": "router_autorouter_autorouter_methodname", "relation": "calls", "context": "call", "confidence": "EXTRACTED", "source_file": "C:\\laragon\\www\\catatan\\vendor\\codeigniter4\\framework\\system\\Router\\AutoRouter.php", "source_location": "L112", "weight": 1.0}, {"source": "router_autorouter_autorouter_scancontrollers", "target": "router_autorouter_autorouter_isvalidsegment", "relation": "calls", "context": "call", "confidence": "EXTRACTED", "source_file": "C:\\laragon\\www\\catatan\\vendor\\codeigniter4\\framework\\system\\Router\\AutoRouter.php", "source_location": "L205", "weight": 1.0}, {"source": "router_autorouter_autorouter_scancontrollers", "target": "router_autorouter_autorouter_setdirectory", "relation": "calls", "context": "call", "confidence": "EXTRACTED", "source_file": "C:\\laragon\\www\\catatan\\vendor\\codeigniter4\\framework\\system\\Router\\AutoRouter.php", "source_location": "L213", "weight": 1.0}, {"source": "router_autorouter_autorouter_setdirectory", "target": "router_autorouter_autorouter_isvalidsegment", "relation": "calls", "context": "call", "confidence": "EXTRACTED", "source_file": "C:\\laragon\\www\\catatan\\vendor\\codeigniter4\\framework\\system\\Router\\AutoRouter.php", "source_location": "L257", "weight": 1.0}], "raw_calls": [{"caller_nid": "router_autorouter_autorouter_getroute", "callee": "explode", "is_member_call": false, "source_file": "C:\\laragon\\www\\catatan\\vendor\\codeigniter4\\framework\\system\\Router\\AutoRouter.php", "source_location": "L68"}, {"caller_nid": "router_autorouter_autorouter_getroute", "callee": "ucfirst", "is_member_call": false, "source_file": "C:\\laragon\\www\\catatan\\vendor\\codeigniter4\\framework\\system\\Router\\AutoRouter.php", "source_location": "L76"}, {"caller_nid": "router_autorouter_autorouter_getroute", "callee": "array_shift", "is_member_call": false, "source_file": "C:\\laragon\\www\\catatan\\vendor\\codeigniter4\\framework\\system\\Router\\AutoRouter.php", "source_location": "L76"}, {"caller_nid": "router_autorouter_autorouter_getroute", "callee": "array_shift", "is_member_call": false, "source_file": "C:\\laragon\\www\\catatan\\vendor\\codeigniter4\\framework\\system\\Router\\AutoRouter.php", "source_location": "L89"}, {"caller_nid": "router_autorouter_autorouter_getroute", "callee": "strtolower", "is_member_call": false, "source_file": "C:\\laragon\\www\\catatan\\vendor\\codeigniter4\\framework\\system\\Router\\AutoRouter.php", "source_location": "L93"}, {"caller_nid": "router_autorouter_autorouter_getroute", "callee": "PageNotFoundException", "is_member_call": false, "source_file": "C:\\laragon\\www\\catatan\\vendor\\codeigniter4\\framework\\system\\Router\\AutoRouter.php", "source_location": "L94"}, {"caller_nid": "router_autorouter_autorouter_getroute", "callee": "str_replace", "is_member_call": false, "source_file": "C:\\laragon\\www\\catatan\\vendor\\codeigniter4\\framework\\system\\Router\\AutoRouter.php", "source_location": "L108"}, {"caller_nid": "router_autorouter_autorouter_getroute", "callee": "strtolower", "is_member_call": false, "source_file": "C:\\laragon\\www\\catatan\\vendor\\codeigniter4\\framework\\system\\Router\\AutoRouter.php", "source_location": "L111"}, {"caller_nid": "router_autorouter_autorouter_getroute", "callee": "strtolower", "is_member_call": false, "source_file": "C:\\laragon\\www\\catatan\\vendor\\codeigniter4\\framework\\system\\Router\\AutoRouter.php", "source_location": "L112"}, {"caller_nid": "router_autorouter_autorouter_getroute", "callee": "is_string", "is_member_call": false, "source_file": "C:\\laragon\\www\\catatan\\vendor\\codeigniter4\\framework\\system\\Router\\AutoRouter.php", "source_location": "L115"}, {"caller_nid": "router_autorouter_autorouter_getroute", "callee": "strtolower", "is_member_call": false, "source_file": "C:\\laragon\\www\\catatan\\vendor\\codeigniter4\\framework\\system\\Router\\AutoRouter.php", "source_location": "L116"}, {"caller_nid": "router_autorouter_autorouter_getroute", "callee": "str_contains", "is_member_call": false, "source_file": "C:\\laragon\\www\\catatan\\vendor\\codeigniter4\\framework\\system\\Router\\AutoRouter.php", "source_location": "L119"}, {"caller_nid": "router_autorouter_autorouter_getroute", "callee": "str_starts_with", "is_member_call": false, "source_file": "C:\\laragon\\www\\catatan\\vendor\\codeigniter4\\framework\\system\\Router\\AutoRouter.php", "source_location": "L125"}, {"caller_nid": "router_autorouter_autorouter_getroute", "callee": "is_file", "is_member_call": false, "source_file": "C:\\laragon\\www\\catatan\\vendor\\codeigniter4\\framework\\system\\Router\\AutoRouter.php", "source_location": "L143"}, {"caller_nid": "router_autorouter_autorouter_getroute", "callee": "PageNotFoundException", "is_member_call": false, "source_file": "C:\\laragon\\www\\catatan\\vendor\\codeigniter4\\framework\\system\\Router\\AutoRouter.php", "source_location": "L144"}, {"caller_nid": "router_autorouter_autorouter_getroute", "callee": "str_contains", "is_member_call": false, "source_file": "C:\\laragon\\www\\catatan\\vendor\\codeigniter4\\framework\\system\\Router\\AutoRouter.php", "source_location": "L151"}, {"caller_nid": "router_autorouter_autorouter_getroute", "callee": "strlen", "is_member_call": false, "source_file": "C:\\laragon\\www\\catatan\\vendor\\codeigniter4\\framework\\system\\Router\\AutoRouter.php", "source_location": "L151"}, {"caller_nid": "router_autorouter_autorouter_getroute", "callee": "ltrim", "is_member_call": false, "source_file": "C:\\laragon\\www\\catatan\\vendor\\codeigniter4\\framework\\system\\Router\\AutoRouter.php", "source_location": "L152"}, {"caller_nid": "router_autorouter_autorouter_getroute", "callee": "str_replace", "is_member_call": false, "source_file": "C:\\laragon\\www\\catatan\\vendor\\codeigniter4\\framework\\system\\Router\\AutoRouter.php", "source_location": "L153"}, {"caller_nid": "router_autorouter_autorouter_scancontrollers", "callee": "array_filter", "is_member_call": false, "source_file": "C:\\laragon\\www\\catatan\\vendor\\codeigniter4\\framework\\system\\Router\\AutoRouter.php", "source_location": "L187"}, {"caller_nid": "router_autorouter_autorouter_scancontrollers", "callee": "array_values", "is_member_call": false, "source_file": "C:\\laragon\\www\\catatan\\vendor\\codeigniter4\\framework\\system\\Router\\AutoRouter.php", "source_location": "L189"}, {"caller_nid": "router_autorouter_autorouter_scancontrollers", "callee": "isset", "is_member_call": false, "source_file": "C:\\laragon\\www\\catatan\\vendor\\codeigniter4\\framework\\system\\Router\\AutoRouter.php", "source_location": "L192"}, {"caller_nid": "router_autorouter_autorouter_scancontrollers", "callee": "count", "is_member_call": false, "source_file": "C:\\laragon\\www\\catatan\\vendor\\codeigniter4\\framework\\system\\Router\\AutoRouter.php", "source_location": "L198"}, {"caller_nid": "router_autorouter_autorouter_scancontrollers", "callee": "ucfirst", "is_member_call": false, "source_file": "C:\\laragon\\www\\catatan\\vendor\\codeigniter4\\framework\\system\\Router\\AutoRouter.php", "source_location": "L201"}, {"caller_nid": "router_autorouter_autorouter_scancontrollers", "callee": "str_replace", "is_member_call": false, "source_file": "C:\\laragon\\www\\catatan\\vendor\\codeigniter4\\framework\\system\\Router\\AutoRouter.php", "source_location": "L202"}, {"caller_nid": "router_autorouter_autorouter_scancontrollers", "callee": "is_file", "is_member_call": false, "source_file": "C:\\laragon\\www\\catatan\\vendor\\codeigniter4\\framework\\system\\Router\\AutoRouter.php", "source_location": "L212"}, {"caller_nid": "router_autorouter_autorouter_scancontrollers", "callee": "is_dir", "is_member_call": false, "source_file": "C:\\laragon\\www\\catatan\\vendor\\codeigniter4\\framework\\system\\Router\\AutoRouter.php", "source_location": "L212"}, {"caller_nid": "router_autorouter_autorouter_scancontrollers", "callee": "array_shift", "is_member_call": false, "source_file": "C:\\laragon\\www\\catatan\\vendor\\codeigniter4\\framework\\system\\Router\\AutoRouter.php", "source_location": "L214"}, {"caller_nid": "router_autorouter_autorouter_isvalidsegment", "callee": "preg_match", "is_member_call": false, "source_file": "C:\\laragon\\www\\catatan\\vendor\\codeigniter4\\framework\\system\\Router\\AutoRouter.php", "source_location": "L233"}, {"caller_nid": "router_autorouter_autorouter_setdirectory", "callee": "explode", "is_member_call": false, "source_file": "C:\\laragon\\www\\catatan\\vendor\\codeigniter4\\framework\\system\\Router\\AutoRouter.php", "source_location": "L254"}, {"caller_nid": "router_autorouter_autorouter_setdirectory", "callee": "trim", "is_member_call": false, "source_file": "C:\\laragon\\www\\catatan\\vendor\\codeigniter4\\framework\\system\\Router\\AutoRouter.php", "source_location": "L254"}, {"caller_nid": "router_autorouter_autorouter_setdirectory", "callee": "trim", "is_member_call": false, "source_file": "C:\\laragon\\www\\catatan\\vendor\\codeigniter4\\framework\\system\\Router\\AutoRouter.php", "source_location": "L264"}, {"caller_nid": "router_autorouter_autorouter_setdirectory", "callee": "trim", "is_member_call": false, "source_file": "C:\\laragon\\www\\catatan\\vendor\\codeigniter4\\framework\\system\\Router\\AutoRouter.php", "source_location": "L266"}, {"caller_nid": "router_autorouter_autorouter_controllername", "callee": "str_replace", "is_member_call": false, "source_file": "C:\\laragon\\www\\catatan\\vendor\\codeigniter4\\framework\\system\\Router\\AutoRouter.php", "source_location": "L284"}, {"caller_nid": "router_autorouter_autorouter_methodname", "callee": "str_replace", "is_member_call": false, "source_file": "C:\\laragon\\www\\catatan\\vendor\\codeigniter4\\framework\\system\\Router\\AutoRouter.php", "source_location": "L291"}]}