{"nodes": [{"id": "c_laragon_www_catatan_vendor_codeigniter4_shield_src_result_php", "label": "Result.php", "file_type": "code", "source_file": "C:\\laragon\\www\\catatan\\vendor\\codeigniter4\\shield\\src\\Result.php", "source_location": "L1"}, {"id": "src_result_result", "label": "Result", "file_type": "code", "source_file": "C:\\laragon\\www\\catatan\\vendor\\codeigniter4\\shield\\src\\Result.php", "source_location": "L18"}, {"id": "src_result_result_construct", "label": ".__construct()", "file_type": "code", "source_file": "C:\\laragon\\www\\catatan\\vendor\\codeigniter4\\shield\\src\\Result.php", "source_location": "L40"}, {"id": "src_result_result_isok", "label": ".isOK()", "file_type": "code", "source_file": "C:\\laragon\\www\\catatan\\vendor\\codeigniter4\\shield\\src\\Result.php", "source_location": "L52"}, {"id": "src_result_result_reason", "label": ".reason()", "file_type": "code", "source_file": "C:\\laragon\\www\\catatan\\vendor\\codeigniter4\\shield\\src\\Result.php", "source_location": "L57"}, {"id": "src_result_result_extrainfo", "label": ".extraInfo()", "file_type": "code", "source_file": "C:\\laragon\\www\\catatan\\vendor\\codeigniter4\\shield\\src\\Result.php", "source_location": "L65"}], "edges": [{"source": "c_laragon_www_catatan_vendor_codeigniter4_shield_src_result_php", "target": "user", "relation": "imports", "context": "import", "confidence": "EXTRACTED", "source_file": "C:\\laragon\\www\\catatan\\vendor\\codeigniter4\\shield\\src\\Result.php", "source_location": "L16", "weight": 1.0}, {"source": "c_laragon_www_catatan_vendor_codeigniter4_shield_src_result_php", "target": "src_result_result", "relation": "contains", "confidence": "EXTRACTED", "source_file": "C:\\laragon\\www\\catatan\\vendor\\codeigniter4\\shield\\src\\Result.php", "source_location": "L18", "weight": 1.0}, {"source": "src_result_result", "target": "src_result_result_construct", "relation": "method", "confidence": "EXTRACTED", "source_file": "C:\\laragon\\www\\catatan\\vendor\\codeigniter4\\shield\\src\\Result.php", "source_location": "L40", "weight": 1.0}, {"source": "src_result_result", "target": "src_result_result_isok", "relation": "method", "confidence": "EXTRACTED", "source_file": "C:\\laragon\\www\\catatan\\vendor\\codeigniter4\\shield\\src\\Result.php", "source_location": "L52", "weight": 1.0}, {"source": "src_result_result", "target": "src_result_result_reason", "relation": "method", "confidence": "EXTRACTED", "source_file": "C:\\laragon\\www\\catatan\\vendor\\codeigniter4\\shield\\src\\Result.php", "source_location": "L57", "weight": 1.0}, {"source": "src_result_result", "target": "src_result_result_extrainfo", "relation": "method", "confidence": "EXTRACTED", "source_file": "C:\\laragon\\www\\catatan\\vendor\\codeigniter4\\shield\\src\\Result.php", "source_location": "L65", "weight": 1.0}], "raw_calls": [{"caller_nid": "src_result_result_construct", "callee": "assert", "is_member_call": false, "source_file": "C:\\laragon\\www\\catatan\\vendor\\codeigniter4\\shield\\src\\Result.php", "source_location": "L43"}, {"caller_nid": "src_result_result_construct", "callee": "property_exists", "is_member_call": false, "source_file": "C:\\laragon\\www\\catatan\\vendor\\codeigniter4\\shield\\src\\Result.php", "source_location": "L43"}]}