{"nodes": [{"id": "c_laragon_www_catatan_app_controllers_cooperative_savingcontroller_php", "label": "SavingController.php", "file_type": "code", "source_file": "C:\\laragon\\www\\catatan\\app\\Controllers\\Cooperative\\SavingController.php", "source_location": "L1"}, {"id": "cooperative_savingcontroller_savingcontroller", "label": "SavingController", "file_type": "code", "source_file": "C:\\laragon\\www\\catatan\\app\\Controllers\\Cooperative\\SavingController.php", "source_location": "L12"}, {"id": "cooperative_savingcontroller_savingcontroller_construct", "label": ".__construct()", "file_type": "code", "source_file": "C:\\laragon\\www\\catatan\\app\\Controllers\\Cooperative\\SavingController.php", "source_location": "L18"}, {"id": "cooperative_savingcontroller_savingcontroller_savings", "label": ".savings()", "file_type": "code", "source_file": "C:\\laragon\\www\\catatan\\app\\Controllers\\Cooperative\\SavingController.php", "source_location": "L28"}, {"id": "cooperative_savingcontroller_savingcontroller_approvesaving", "label": ".approveSaving()", "file_type": "code", "source_file": "C:\\laragon\\www\\catatan\\app\\Controllers\\Cooperative\\SavingController.php", "source_location": "L45"}, {"id": "cooperative_savingcontroller_savingcontroller_rejectsaving", "label": ".rejectSaving()", "file_type": "code", "source_file": "C:\\laragon\\www\\catatan\\app\\Controllers\\Cooperative\\SavingController.php", "source_location": "L126"}], "edges": [{"source": "c_laragon_www_catatan_app_controllers_cooperative_savingcontroller_php", "target": "basecontroller", "relation": "imports", "context": "import", "confidence": "EXTRACTED", "source_file": "C:\\laragon\\www\\catatan\\app\\Controllers\\Cooperative\\SavingController.php", "source_location": "L5", "weight": 1.0}, {"source": "c_laragon_www_catatan_app_controllers_cooperative_savingcontroller_php", "target": "kopsimpananmodel", "relation": "imports", "context": "import", "confidence": "EXTRACTED", "source_file": "C:\\laragon\\www\\catatan\\app\\Controllers\\Cooperative\\SavingController.php", "source_location": "L6", "weight": 1.0}, {"source": "c_laragon_www_catatan_app_controllers_cooperative_savingcontroller_php", "target": "kopkasinternalmodel", "relation": "imports", "context": "import", "confidence": "EXTRACTED", "source_file": "C:\\laragon\\www\\catatan\\app\\Controllers\\Cooperative\\SavingController.php", "source_location": "L7", "weight": 1.0}, {"source": "c_laragon_www_catatan_app_controllers_cooperative_savingcontroller_php", "target": "auditlogmodel", "relation": "imports", "context": "import", "confidence": "EXTRACTED", "source_file": "C:\\laragon\\www\\catatan\\app\\Controllers\\Cooperative\\SavingController.php", "source_location": "L8", "weight": 1.0}, {"source": "c_laragon_www_catatan_app_controllers_cooperative_savingcontroller_php", "target": "kopanggotamodel", "relation": "imports", "context": "import", "confidence": "EXTRACTED", "source_file": "C:\\laragon\\www\\catatan\\app\\Controllers\\Cooperative\\SavingController.php", "source_location": "L9", "weight": 1.0}, {"source": "c_laragon_www_catatan_app_controllers_cooperative_savingcontroller_php", "target": "kopsettingmodel", "relation": "imports", "context": "import", "confidence": "EXTRACTED", "source_file": "C:\\laragon\\www\\catatan\\app\\Controllers\\Cooperative\\SavingController.php", "source_location": "L10", "weight": 1.0}, {"source": "c_laragon_www_catatan_app_controllers_cooperative_savingcontroller_php", "target": "cooperative_savingcontroller_savingcontroller", "relation": "contains", "confidence": "EXTRACTED", "source_file": "C:\\laragon\\www\\catatan\\app\\Controllers\\Cooperative\\SavingController.php", "source_location": "L12", "weight": 1.0}, {"source": "cooperative_savingcontroller_savingcontroller", "target": "cooperative_savingcontroller_savingcontroller_construct", "relation": "method", "confidence": "EXTRACTED", "source_file": "C:\\laragon\\www\\catatan\\app\\Controllers\\Cooperative\\SavingController.php", "source_location": "L18", "weight": 1.0}, {"source": "cooperative_savingcontroller_savingcontroller", "target": "cooperative_savingcontroller_savingcontroller_savings", "relation": "method", "confidence": "EXTRACTED", "source_file": "C:\\laragon\\www\\catatan\\app\\Controllers\\Cooperative\\SavingController.php", "source_location": "L28", "weight": 1.0}, {"source": "cooperative_savingcontroller_savingcontroller", "target": "cooperative_savingcontroller_savingcontroller_approvesaving", "relation": "method", "confidence": "EXTRACTED", "source_file": "C:\\laragon\\www\\catatan\\app\\Controllers\\Cooperative\\SavingController.php", "source_location": "L45", "weight": 1.0}, {"source": "cooperative_savingcontroller_savingcontroller", "target": "cooperative_savingcontroller_savingcontroller_rejectsaving", "relation": "method", "confidence": "EXTRACTED", "source_file": "C:\\laragon\\www\\catatan\\app\\Controllers\\Cooperative\\SavingController.php", "source_location": "L126", "weight": 1.0}], "raw_calls": [{"caller_nid": "cooperative_savingcontroller_savingcontroller_savings", "callee": "findAll", "is_member_call": true, "source_file": "C:\\laragon\\www\\catatan\\app\\Controllers\\Cooperative\\SavingController.php", "source_location": "L30"}, {"caller_nid": "cooperative_savingcontroller_savingcontroller_savings", "callee": "orderBy", "is_member_call": true, "source_file": "C:\\laragon\\www\\catatan\\app\\Controllers\\Cooperative\\SavingController.php", "source_location": "L30"}, {"caller_nid": "cooperative_savingcontroller_savingcontroller_savings", "callee": "join", "is_member_call": true, "source_file": "C:\\laragon\\www\\catatan\\app\\Controllers\\Cooperative\\SavingController.php", "source_location": "L30"}, {"caller_nid": "cooperative_savingcontroller_savingcontroller_savings", "callee": "join", "is_member_call": true, "source_file": "C:\\laragon\\www\\catatan\\app\\Controllers\\Cooperative\\SavingController.php", "source_location": "L30"}, {"caller_nid": "cooperative_savingcontroller_savingcontroller_savings", "callee": "select", "is_member_call": true, "source_file": "C:\\laragon\\www\\catatan\\app\\Controllers\\Cooperative\\SavingController.php", "source_location": "L30"}, {"caller_nid": "cooperative_savingcontroller_savingcontroller_savings", "callee": "view", "is_member_call": false, "source_file": "C:\\laragon\\www\\catatan\\app\\Controllers\\Cooperative\\SavingController.php", "source_location": "L36"}, {"caller_nid": "cooperative_savingcontroller_savingcontroller_approvesaving", "callee": "find", "is_member_call": true, "source_file": "C:\\laragon\\www\\catatan\\app\\Controllers\\Cooperative\\SavingController.php", "source_location": "L47"}, {"caller_nid": "cooperative_savingcontroller_savingcontroller_approvesaving", "callee": "with", "is_member_call": true, "source_file": "C:\\laragon\\www\\catatan\\app\\Controllers\\Cooperative\\SavingController.php", "source_location": "L49"}, {"caller_nid": "cooperative_savingcontroller_savingcontroller_approvesaving", "callee": "back", "is_member_call": true, "source_file": "C:\\laragon\\www\\catatan\\app\\Controllers\\Cooperative\\SavingController.php", "source_location": "L49"}, {"caller_nid": "cooperative_savingcontroller_savingcontroller_approvesaving", "callee": "redirect", "is_member_call": false, "source_file": "C:\\laragon\\www\\catatan\\app\\Controllers\\Cooperative\\SavingController.php", "source_location": "L49"}, {"caller_nid": "cooperative_savingcontroller_savingcontroller_approvesaving", "callee": "\\Config\\Database", "is_member_call": false, "source_file": "C:\\laragon\\www\\catatan\\app\\Controllers\\Cooperative\\SavingController.php", "source_location": "L52"}, {"caller_nid": "cooperative_savingcontroller_savingcontroller_approvesaving", "callee": "transStart", "is_member_call": true, "source_file": "C:\\laragon\\www\\catatan\\app\\Controllers\\Cooperative\\SavingController.php", "source_location": "L53"}, {"caller_nid": "cooperative_savingcontroller_savingcontroller_approvesaving", "callee": "update", "is_member_call": true, "source_file": "C:\\laragon\\www\\catatan\\app\\Controllers\\Cooperative\\SavingController.php", "source_location": "L56"}, {"caller_nid": "cooperative_savingcontroller_savingcontroller_approvesaving", "callee": "id", "is_member_call": true, "source_file": "C:\\laragon\\www\\catatan\\app\\Controllers\\Cooperative\\SavingController.php", "source_location": "L58"}, {"caller_nid": "cooperative_savingcontroller_savingcontroller_approvesaving", "callee": "auth", "is_member_call": false, "source_file": "C:\\laragon\\www\\catatan\\app\\Controllers\\Cooperative\\SavingController.php", "source_location": "L58"}, {"caller_nid": "cooperative_savingcontroller_savingcontroller_approvesaving", "callee": "date", "is_member_call": false, "source_file": "C:\\laragon\\www\\catatan\\app\\Controllers\\Cooperative\\SavingController.php", "source_location": "L59"}, {"caller_nid": "cooperative_savingcontroller_savingcontroller_approvesaving", "callee": "floatval", "is_member_call": false, "source_file": "C:\\laragon\\www\\catatan\\app\\Controllers\\Cooperative\\SavingController.php", "source_location": "L64"}, {"caller_nid": "cooperative_savingcontroller_savingcontroller_approvesaving", "callee": "KopSettingModel", "is_member_call": false, "source_file": "C:\\laragon\\www\\catatan\\app\\Controllers\\Cooperative\\SavingController.php", "source_location": "L64"}, {"caller_nid": "cooperative_savingcontroller_savingcontroller_approvesaving", "callee": "floatval", "is_member_call": false, "source_file": "C:\\laragon\\www\\catatan\\app\\Controllers\\Cooperative\\SavingController.php", "source_location": "L65"}, {"caller_nid": "cooperative_savingcontroller_savingcontroller_approvesaving", "callee": "KopSettingModel", "is_member_call": false, "source_file": "C:\\laragon\\www\\catatan\\app\\Controllers\\Cooperative\\SavingController.php", "source_location": "L65"}, {"caller_nid": "cooperative_savingcontroller_savingcontroller_approvesaving", "callee": "intval", "is_member_call": false, "source_file": "C:\\laragon\\www\\catatan\\app\\Controllers\\Cooperative\\SavingController.php", "source_location": "L66"}, {"caller_nid": "cooperative_savingcontroller_savingcontroller_approvesaving", "callee": "date", "is_member_call": false, "source_file": "C:\\laragon\\www\\catatan\\app\\Controllers\\Cooperative\\SavingController.php", "source_location": "L66"}, {"caller_nid": "cooperative_savingcontroller_savingcontroller_approvesaving", "callee": "insert", "is_member_call": true, "source_file": "C:\\laragon\\www\\catatan\\app\\Controllers\\Cooperative\\SavingController.php", "source_location": "L70"}, {"caller_nid": "cooperative_savingcontroller_savingcontroller_approvesaving", "callee": "id", "is_member_call": true, "source_file": "C:\\laragon\\www\\catatan\\app\\Controllers\\Cooperative\\SavingController.php", "source_location": "L80"}, {"caller_nid": "cooperative_savingcontroller_savingcontroller_approvesaving", "callee": "auth", "is_member_call": false, "source_file": "C:\\laragon\\www\\catatan\\app\\Controllers\\Cooperative\\SavingController.php", "source_location": "L80"}, {"caller_nid": "cooperative_savingcontroller_savingcontroller_approvesaving", "callee": "date", "is_member_call": false, "source_file": "C:\\laragon\\www\\catatan\\app\\Controllers\\Cooperative\\SavingController.php", "source_location": "L81"}, {"caller_nid": "cooperative_savingcontroller_savingcontroller_approvesaving", "callee": "date", "is_member_call": false, "source_file": "C:\\laragon\\www\\catatan\\app\\Controllers\\Cooperative\\SavingController.php", "source_location": "L82"}, {"caller_nid": "cooperative_savingcontroller_savingcontroller_approvesaving", "callee": "insert", "is_member_call": true, "source_file": "C:\\laragon\\www\\catatan\\app\\Controllers\\Cooperative\\SavingController.php", "source_location": "L86"}, {"caller_nid": "cooperative_savingcontroller_savingcontroller_approvesaving", "callee": "id", "is_member_call": true, "source_file": "C:\\laragon\\www\\catatan\\app\\Controllers\\Cooperative\\SavingController.php", "source_location": "L96"}, {"caller_nid": "cooperative_savingcontroller_savingcontroller_approvesaving", "callee": "auth", "is_member_call": false, "source_file": "C:\\laragon\\www\\catatan\\app\\Controllers\\Cooperative\\SavingController.php", "source_location": "L96"}, {"caller_nid": "cooperative_savingcontroller_savingcontroller_approvesaving", "callee": "date", "is_member_call": false, "source_file": "C:\\laragon\\www\\catatan\\app\\Controllers\\Cooperative\\SavingController.php", "source_location": "L97"}, {"caller_nid": "cooperative_savingcontroller_savingcontroller_approvesaving", "callee": "date", "is_member_call": false, "source_file": "C:\\laragon\\www\\catatan\\app\\Controllers\\Cooperative\\SavingController.php", "source_location": "L98"}, {"caller_nid": "cooperative_savingcontroller_savingcontroller_approvesaving", "callee": "transComplete", "is_member_call": true, "source_file": "C:\\laragon\\www\\catatan\\app\\Controllers\\Cooperative\\SavingController.php", "source_location": "L103"}, {"caller_nid": "cooperative_savingcontroller_savingcontroller_approvesaving", "callee": "transStatus", "is_member_call": true, "source_file": "C:\\laragon\\www\\catatan\\app\\Controllers\\Cooperative\\SavingController.php", "source_location": "L105"}, {"caller_nid": "cooperative_savingcontroller_savingcontroller_approvesaving", "callee": "with", "is_member_call": true, "source_file": "C:\\laragon\\www\\catatan\\app\\Controllers\\Cooperative\\SavingController.php", "source_location": "L106"}, {"caller_nid": "cooperative_savingcontroller_savingcontroller_approvesaving", "callee": "back", "is_member_call": true, "source_file": "C:\\laragon\\www\\catatan\\app\\Controllers\\Cooperative\\SavingController.php", "source_location": "L106"}, {"caller_nid": "cooperative_savingcontroller_savingcontroller_approvesaving", "callee": "redirect", "is_member_call": false, "source_file": "C:\\laragon\\www\\catatan\\app\\Controllers\\Cooperative\\SavingController.php", "source_location": "L106"}, {"caller_nid": "cooperative_savingcontroller_savingcontroller_approvesaving", "callee": "find", "is_member_call": true, "source_file": "C:\\laragon\\www\\catatan\\app\\Controllers\\Cooperative\\SavingController.php", "source_location": "L109"}, {"caller_nid": "cooperative_savingcontroller_savingcontroller_approvesaving", "callee": "find", "is_member_call": true, "source_file": "C:\\laragon\\www\\catatan\\app\\Controllers\\Cooperative\\SavingController.php", "source_location": "L110"}, {"caller_nid": "cooperative_savingcontroller_savingcontroller_approvesaving", "callee": "getProvider", "is_member_call": true, "source_file": "C:\\laragon\\www\\catatan\\app\\Controllers\\Cooperative\\SavingController.php", "source_location": "L110"}, {"caller_nid": "cooperative_savingcontroller_savingcontroller_approvesaving", "callee": "auth", "is_member_call": false, "source_file": "C:\\laragon\\www\\catatan\\app\\Controllers\\Cooperative\\SavingController.php", "source_location": "L110"}, {"caller_nid": "cooperative_savingcontroller_savingcontroller_approvesaving", "callee": "AuditLogModel", "is_member_call": false, "source_file": "C:\\laragon\\www\\catatan\\app\\Controllers\\Cooperative\\SavingController.php", "source_location": "L113"}, {"caller_nid": "cooperative_savingcontroller_savingcontroller_approvesaving", "callee": "strtoupper", "is_member_call": false, "source_file": "C:\\laragon\\www\\catatan\\app\\Controllers\\Cooperative\\SavingController.php", "source_location": "L113"}, {"caller_nid": "cooperative_savingcontroller_savingcontroller_approvesaving", "callee": "strtoupper", "is_member_call": false, "source_file": "C:\\laragon\\www\\catatan\\app\\Controllers\\Cooperative\\SavingController.php", "source_location": "L113"}, {"caller_nid": "cooperative_savingcontroller_savingcontroller_approvesaving", "callee": "number_format", "is_member_call": false, "source_file": "C:\\laragon\\www\\catatan\\app\\Controllers\\Cooperative\\SavingController.php", "source_location": "L113"}, {"caller_nid": "cooperative_savingcontroller_savingcontroller_approvesaving", "callee": "with", "is_member_call": true, "source_file": "C:\\laragon\\www\\catatan\\app\\Controllers\\Cooperative\\SavingController.php", "source_location": "L115"}, {"caller_nid": "cooperative_savingcontroller_savingcontroller_approvesaving", "callee": "back", "is_member_call": true, "source_file": "C:\\laragon\\www\\catatan\\app\\Controllers\\Cooperative\\SavingController.php", "source_location": "L115"}, {"caller_nid": "cooperative_savingcontroller_savingcontroller_approvesaving", "callee": "redirect", "is_member_call": false, "source_file": "C:\\laragon\\www\\catatan\\app\\Controllers\\Cooperative\\SavingController.php", "source_location": "L115"}, {"caller_nid": "cooperative_savingcontroller_savingcontroller_approvesaving", "callee": "transRollback", "is_member_call": true, "source_file": "C:\\laragon\\www\\catatan\\app\\Controllers\\Cooperative\\SavingController.php", "source_location": "L118"}, {"caller_nid": "cooperative_savingcontroller_savingcontroller_approvesaving", "callee": "with", "is_member_call": true, "source_file": "C:\\laragon\\www\\catatan\\app\\Controllers\\Cooperative\\SavingController.php", "source_location": "L119"}, {"caller_nid": "cooperative_savingcontroller_savingcontroller_approvesaving", "callee": "back", "is_member_call": true, "source_file": "C:\\laragon\\www\\catatan\\app\\Controllers\\Cooperative\\SavingController.php", "source_location": "L119"}, {"caller_nid": "cooperative_savingcontroller_savingcontroller_approvesaving", "callee": "redirect", "is_member_call": false, "source_file": "C:\\laragon\\www\\catatan\\app\\Controllers\\Cooperative\\SavingController.php", "source_location": "L119"}, {"caller_nid": "cooperative_savingcontroller_savingcontroller_approvesaving", "callee": "getMessage", "is_member_call": true, "source_file": "C:\\laragon\\www\\catatan\\app\\Controllers\\Cooperative\\SavingController.php", "source_location": "L119"}, {"caller_nid": "cooperative_savingcontroller_savingcontroller_rejectsaving", "callee": "find", "is_member_call": true, "source_file": "C:\\laragon\\www\\catatan\\app\\Controllers\\Cooperative\\SavingController.php", "source_location": "L128"}, {"caller_nid": "cooperative_savingcontroller_savingcontroller_rejectsaving", "callee": "with", "is_member_call": true, "source_file": "C:\\laragon\\www\\catatan\\app\\Controllers\\Cooperative\\SavingController.php", "source_location": "L130"}, {"caller_nid": "cooperative_savingcontroller_savingcontroller_rejectsaving", "callee": "back", "is_member_call": true, "source_file": "C:\\laragon\\www\\catatan\\app\\Controllers\\Cooperative\\SavingController.php", "source_location": "L130"}, {"caller_nid": "cooperative_savingcontroller_savingcontroller_rejectsaving", "callee": "redirect", "is_member_call": false, "source_file": "C:\\laragon\\www\\catatan\\app\\Controllers\\Cooperative\\SavingController.php", "source_location": "L130"}, {"caller_nid": "cooperative_savingcontroller_savingcontroller_rejectsaving", "callee": "update", "is_member_call": true, "source_file": "C:\\laragon\\www\\catatan\\app\\Controllers\\Cooperative\\SavingController.php", "source_location": "L133"}, {"caller_nid": "cooperative_savingcontroller_savingcontroller_rejectsaving", "callee": "id", "is_member_call": true, "source_file": "C:\\laragon\\www\\catatan\\app\\Controllers\\Cooperative\\SavingController.php", "source_location": "L135"}, {"caller_nid": "cooperative_savingcontroller_savingcontroller_rejectsaving", "callee": "auth", "is_member_call": false, "source_file": "C:\\laragon\\www\\catatan\\app\\Controllers\\Cooperative\\SavingController.php", "source_location": "L135"}, {"caller_nid": "cooperative_savingcontroller_savingcontroller_rejectsaving", "callee": "date", "is_member_call": false, "source_file": "C:\\laragon\\www\\catatan\\app\\Controllers\\Cooperative\\SavingController.php", "source_location": "L136"}, {"caller_nid": "cooperative_savingcontroller_savingcontroller_rejectsaving", "callee": "find", "is_member_call": true, "source_file": "C:\\laragon\\www\\catatan\\app\\Controllers\\Cooperative\\SavingController.php", "source_location": "L139"}, {"caller_nid": "cooperative_savingcontroller_savingcontroller_rejectsaving", "callee": "find", "is_member_call": true, "source_file": "C:\\laragon\\www\\catatan\\app\\Controllers\\Cooperative\\SavingController.php", "source_location": "L140"}, {"caller_nid": "cooperative_savingcontroller_savingcontroller_rejectsaving", "callee": "getProvider", "is_member_call": true, "source_file": "C:\\laragon\\www\\catatan\\app\\Controllers\\Cooperative\\SavingController.php", "source_location": "L140"}, {"caller_nid": "cooperative_savingcontroller_savingcontroller_rejectsaving", "callee": "auth", "is_member_call": false, "source_file": "C:\\laragon\\www\\catatan\\app\\Controllers\\Cooperative\\SavingController.php", "source_location": "L140"}, {"caller_nid": "cooperative_savingcontroller_savingcontroller_rejectsaving", "callee": "AuditLogModel", "is_member_call": false, "source_file": "C:\\laragon\\www\\catatan\\app\\Controllers\\Cooperative\\SavingController.php", "source_location": "L143"}, {"caller_nid": "cooperative_savingcontroller_savingcontroller_rejectsaving", "callee": "strtoupper", "is_member_call": false, "source_file": "C:\\laragon\\www\\catatan\\app\\Controllers\\Cooperative\\SavingController.php", "source_location": "L143"}, {"caller_nid": "cooperative_savingcontroller_savingcontroller_rejectsaving", "callee": "strtoupper", "is_member_call": false, "source_file": "C:\\laragon\\www\\catatan\\app\\Controllers\\Cooperative\\SavingController.php", "source_location": "L143"}, {"caller_nid": "cooperative_savingcontroller_savingcontroller_rejectsaving", "callee": "number_format", "is_member_call": false, "source_file": "C:\\laragon\\www\\catatan\\app\\Controllers\\Cooperative\\SavingController.php", "source_location": "L143"}, {"caller_nid": "cooperative_savingcontroller_savingcontroller_rejectsaving", "callee": "with", "is_member_call": true, "source_file": "C:\\laragon\\www\\catatan\\app\\Controllers\\Cooperative\\SavingController.php", "source_location": "L145"}, {"caller_nid": "cooperative_savingcontroller_savingcontroller_rejectsaving", "callee": "back", "is_member_call": true, "source_file": "C:\\laragon\\www\\catatan\\app\\Controllers\\Cooperative\\SavingController.php", "source_location": "L145"}, {"caller_nid": "cooperative_savingcontroller_savingcontroller_rejectsaving", "callee": "redirect", "is_member_call": false, "source_file": "C:\\laragon\\www\\catatan\\app\\Controllers\\Cooperative\\SavingController.php", "source_location": "L145"}]}