{"nodes": [{"id": "c_laragon_www_catatan_vendor_mikey179_vfsstream_composer_json", "label": "composer.json", "file_type": "code", "source_file": "C:\\laragon\\www\\catatan\\vendor\\mikey179\\vfsstream\\composer.json", "source_location": "L1"}, {"id": "vfsstream_composer_name", "label": "name", "file_type": "code", "source_file": "C:\\laragon\\www\\catatan\\vendor\\mikey179\\vfsstream\\composer.json", "source_location": "L2"}, {"id": "vfsstream_composer_type", "label": "type", "file_type": "code", "source_file": "C:\\laragon\\www\\catatan\\vendor\\mikey179\\vfsstream\\composer.json", "source_location": "L3"}, {"id": "vfsstream_composer_homepage", "label": "homepage", "file_type": "code", "source_file": "C:\\laragon\\www\\catatan\\vendor\\mikey179\\vfsstream\\composer.json", "source_location": "L4"}, {"id": "vfsstream_composer_description", "label": "description", "file_type": "code", "source_file": "C:\\laragon\\www\\catatan\\vendor\\mikey179\\vfsstream\\composer.json", "source_location": "L5"}, {"id": "vfsstream_composer_license", "label": "license", "file_type": "code", "source_file": "C:\\laragon\\www\\catatan\\vendor\\mikey179\\vfsstream\\composer.json", "source_location": "L6"}, {"id": "vfsstream_composer_authors", "label": "authors", "file_type": "code", "source_file": "C:\\laragon\\www\\catatan\\vendor\\mikey179\\vfsstream\\composer.json", "source_location": "L7"}, {"id": "vfsstream_composer_support", "label": "support", "file_type": "code", "source_file": "C:\\laragon\\www\\catatan\\vendor\\mikey179\\vfsstream\\composer.json", "source_location": "L14"}, {"id": "vfsstream_composer_support_issues", "label": "issues", "file_type": "code", "source_file": "C:\\laragon\\www\\catatan\\vendor\\mikey179\\vfsstream\\composer.json", "source_location": "L15"}, {"id": "vfsstream_composer_support_source", "label": "source", "file_type": "code", "source_file": "C:\\laragon\\www\\catatan\\vendor\\mikey179\\vfsstream\\composer.json", "source_location": "L16"}, {"id": "vfsstream_composer_support_wiki", "label": "wiki", "file_type": "code", "source_file": "C:\\laragon\\www\\catatan\\vendor\\mikey179\\vfsstream\\composer.json", "source_location": "L17"}, {"id": "vfsstream_composer_require", "label": "require", "file_type": "code", "source_file": "C:\\laragon\\www\\catatan\\vendor\\mikey179\\vfsstream\\composer.json", "source_location": "L19"}, {"id": "vfsstream_composer_require_php", "label": "php", "file_type": "code", "source_file": "C:\\laragon\\www\\catatan\\vendor\\mikey179\\vfsstream\\composer.json", "source_location": "L20"}, {"id": "vfsstream_composer_require_dev", "label": "require-dev", "file_type": "code", "source_file": "C:\\laragon\\www\\catatan\\vendor\\mikey179\\vfsstream\\composer.json", "source_location": "L22"}, {"id": "vfsstream_composer_require_dev_phpunit_phpunit", "label": "phpunit/phpunit", "file_type": "code", "source_file": "C:\\laragon\\www\\catatan\\vendor\\mikey179\\vfsstream\\composer.json", "source_location": "L23"}, {"id": "vfsstream_composer_require_dev_yoast_phpunit_polyfills", "label": "yoast/phpunit-polyfills", "file_type": "code", "source_file": "C:\\laragon\\www\\catatan\\vendor\\mikey179\\vfsstream\\composer.json", "source_location": "L24"}, {"id": "vfsstream_composer_autoload", "label": "autoload", "file_type": "code", "source_file": "C:\\laragon\\www\\catatan\\vendor\\mikey179\\vfsstream\\composer.json", "source_location": "L26"}, {"id": "vfsstream_composer_autoload_psr_0", "label": "psr-0", "file_type": "code", "source_file": "C:\\laragon\\www\\catatan\\vendor\\mikey179\\vfsstream\\composer.json", "source_location": "L27"}, {"id": "vfsstream_composer_psr_0_org_bovigo_vfs", "label": "org\\\\bovigo\\\\vfs\\\\", "file_type": "code", "source_file": "C:\\laragon\\www\\catatan\\vendor\\mikey179\\vfsstream\\composer.json", "source_location": "L27"}, {"id": "vfsstream_composer_scripts", "label": "scripts", "file_type": "code", "source_file": "C:\\laragon\\www\\catatan\\vendor\\mikey179\\vfsstream\\composer.json", "source_location": "L29"}, {"id": "vfsstream_composer_scripts_test", "label": "test", "file_type": "code", "source_file": "C:\\laragon\\www\\catatan\\vendor\\mikey179\\vfsstream\\composer.json", "source_location": "L30"}, {"id": "vfsstream_composer_extra", "label": "extra", "file_type": "code", "source_file": "C:\\laragon\\www\\catatan\\vendor\\mikey179\\vfsstream\\composer.json", "source_location": "L32"}, {"id": "vfsstream_composer_extra_branch_alias", "label": "branch-alias", "file_type": "code", "source_file": "C:\\laragon\\www\\catatan\\vendor\\mikey179\\vfsstream\\composer.json", "source_location": "L33"}, {"id": "vfsstream_composer_branch_alias_dev_master", "label": "dev-master", "file_type": "code", "source_file": "C:\\laragon\\www\\catatan\\vendor\\mikey179\\vfsstream\\composer.json", "source_location": "L34"}], "edges": [{"source": "c_laragon_www_catatan_vendor_mikey179_vfsstream_composer_json", "target": "vfsstream_composer_name", "relation": "contains", "confidence": "EXTRACTED", "source_file": "C:\\laragon\\www\\catatan\\vendor\\mikey179\\vfsstream\\composer.json", "source_location": "L2", "weight": 1.0}, {"source": "c_laragon_www_catatan_vendor_mikey179_vfsstream_composer_json", "target": "vfsstream_composer_type", "relation": "contains", "confidence": "EXTRACTED", "source_file": "C:\\laragon\\www\\catatan\\vendor\\mikey179\\vfsstream\\composer.json", "source_location": "L3", "weight": 1.0}, {"source": "c_laragon_www_catatan_vendor_mikey179_vfsstream_composer_json", "target": "vfsstream_composer_homepage", "relation": "contains", "confidence": "EXTRACTED", "source_file": "C:\\laragon\\www\\catatan\\vendor\\mikey179\\vfsstream\\composer.json", "source_location": "L4", "weight": 1.0}, {"source": "c_laragon_www_catatan_vendor_mikey179_vfsstream_composer_json", "target": "vfsstream_composer_description", "relation": "contains", "confidence": "EXTRACTED", "source_file": "C:\\laragon\\www\\catatan\\vendor\\mikey179\\vfsstream\\composer.json", "source_location": "L5", "weight": 1.0}, {"source": "c_laragon_www_catatan_vendor_mikey179_vfsstream_composer_json", "target": "vfsstream_composer_license", "relation": "contains", "confidence": "EXTRACTED", "source_file": "C:\\laragon\\www\\catatan\\vendor\\mikey179\\vfsstream\\composer.json", "source_location": "L6", "weight": 1.0}, {"source": "c_laragon_www_catatan_vendor_mikey179_vfsstream_composer_json", "target": "vfsstream_composer_authors", "relation": "contains", "confidence": "EXTRACTED", "source_file": "C:\\laragon\\www\\catatan\\vendor\\mikey179\\vfsstream\\composer.json", "source_location": "L7", "weight": 1.0}, {"source": "c_laragon_www_catatan_vendor_mikey179_vfsstream_composer_json", "target": "vfsstream_composer_support", "relation": "contains", "confidence": "EXTRACTED", "source_file": "C:\\laragon\\www\\catatan\\vendor\\mikey179\\vfsstream\\composer.json", "source_location": "L14", "weight": 1.0}, {"source": "vfsstream_composer_support", "target": "vfsstream_composer_support_issues", "relation": "contains", "confidence": "EXTRACTED", "source_file": "C:\\laragon\\www\\catatan\\vendor\\mikey179\\vfsstream\\composer.json", "source_location": "L15", "weight": 1.0}, {"source": "vfsstream_composer_support", "target": "vfsstream_composer_support_source", "relation": "contains", "confidence": "EXTRACTED", "source_file": "C:\\laragon\\www\\catatan\\vendor\\mikey179\\vfsstream\\composer.json", "source_location": "L16", "weight": 1.0}, {"source": "vfsstream_composer_support", "target": "vfsstream_composer_support_wiki", "relation": "contains", "confidence": "EXTRACTED", "source_file": "C:\\laragon\\www\\catatan\\vendor\\mikey179\\vfsstream\\composer.json", "source_location": "L17", "weight": 1.0}, {"source": "c_laragon_www_catatan_vendor_mikey179_vfsstream_composer_json", "target": "vfsstream_composer_require", "relation": "contains", "confidence": "EXTRACTED", "source_file": "C:\\laragon\\www\\catatan\\vendor\\mikey179\\vfsstream\\composer.json", "source_location": "L19", "weight": 1.0}, {"source": "vfsstream_composer_require", "target": "vfsstream_composer_require_php", "relation": "contains", "confidence": "EXTRACTED", "source_file": "C:\\laragon\\www\\catatan\\vendor\\mikey179\\vfsstream\\composer.json", "source_location": "L20", "weight": 1.0}, {"source": "c_laragon_www_catatan_vendor_mikey179_vfsstream_composer_json", "target": "vfsstream_composer_require_dev", "relation": "contains", "confidence": "EXTRACTED", "source_file": "C:\\laragon\\www\\catatan\\vendor\\mikey179\\vfsstream\\composer.json", "source_location": "L22", "weight": 1.0}, {"source": "vfsstream_composer_require_dev", "target": "vfsstream_composer_require_dev_phpunit_phpunit", "relation": "contains", "confidence": "EXTRACTED", "source_file": "C:\\laragon\\www\\catatan\\vendor\\mikey179\\vfsstream\\composer.json", "source_location": "L23", "weight": 1.0}, {"source": "vfsstream_composer_require_dev", "target": "vfsstream_composer_require_dev_yoast_phpunit_polyfills", "relation": "contains", "confidence": "EXTRACTED", "source_file": "C:\\laragon\\www\\catatan\\vendor\\mikey179\\vfsstream\\composer.json", "source_location": "L24", "weight": 1.0}, {"source": "c_laragon_www_catatan_vendor_mikey179_vfsstream_composer_json", "target": "vfsstream_composer_autoload", "relation": "contains", "confidence": "EXTRACTED", "source_file": "C:\\laragon\\www\\catatan\\vendor\\mikey179\\vfsstream\\composer.json", "source_location": "L26", "weight": 1.0}, {"source": "vfsstream_composer_autoload", "target": "vfsstream_composer_autoload_psr_0", "relation": "contains", "confidence": "EXTRACTED", "source_file": "C:\\laragon\\www\\catatan\\vendor\\mikey179\\vfsstream\\composer.json", "source_location": "L27", "weight": 1.0}, {"source": "vfsstream_composer_autoload_psr_0", "target": "vfsstream_composer_psr_0_org_bovigo_vfs", "relation": "contains", "confidence": "EXTRACTED", "source_file": "C:\\laragon\\www\\catatan\\vendor\\mikey179\\vfsstream\\composer.json", "source_location": "L27", "weight": 1.0}, {"source": "c_laragon_www_catatan_vendor_mikey179_vfsstream_composer_json", "target": "vfsstream_composer_scripts", "relation": "contains", "confidence": "EXTRACTED", "source_file": "C:\\laragon\\www\\catatan\\vendor\\mikey179\\vfsstream\\composer.json", "source_location": "L29", "weight": 1.0}, {"source": "vfsstream_composer_scripts", "target": "vfsstream_composer_scripts_test", "relation": "contains", "confidence": "EXTRACTED", "source_file": "C:\\laragon\\www\\catatan\\vendor\\mikey179\\vfsstream\\composer.json", "source_location": "L30", "weight": 1.0}, {"source": "c_laragon_www_catatan_vendor_mikey179_vfsstream_composer_json", "target": "vfsstream_composer_extra", "relation": "contains", "confidence": "EXTRACTED", "source_file": "C:\\laragon\\www\\catatan\\vendor\\mikey179\\vfsstream\\composer.json", "source_location": "L32", "weight": 1.0}, {"source": "vfsstream_composer_extra", "target": "vfsstream_composer_extra_branch_alias", "relation": "contains", "confidence": "EXTRACTED", "source_file": "C:\\laragon\\www\\catatan\\vendor\\mikey179\\vfsstream\\composer.json", "source_location": "L33", "weight": 1.0}, {"source": "vfsstream_composer_extra_branch_alias", "target": "vfsstream_composer_branch_alias_dev_master", "relation": "contains", "confidence": "EXTRACTED", "source_file": "C:\\laragon\\www\\catatan\\vendor\\mikey179\\vfsstream\\composer.json", "source_location": "L34", "weight": 1.0}]}