{"nodes": [{"id": "c_laragon_www_catatan_vendor_codeigniter4_framework_system_cache_cacheinterface_php", "label": "CacheInterface.php", "file_type": "code", "source_file": "C:\\laragon\\www\\catatan\\vendor\\codeigniter4\\framework\\system\\Cache\\CacheInterface.php", "source_location": "L1"}, {"id": "cache_cacheinterface_initialize", "label": "initialize()", "file_type": "code", "source_file": "C:\\laragon\\www\\catatan\\vendor\\codeigniter4\\framework\\system\\Cache\\CacheInterface.php", "source_location": "L23"}, {"id": "cache_cacheinterface_get", "label": "get()", "file_type": "code", "source_file": "C:\\laragon\\www\\catatan\\vendor\\codeigniter4\\framework\\system\\Cache\\CacheInterface.php", "source_location": "L32"}, {"id": "cache_cacheinterface_save", "label": "save()", "file_type": "code", "source_file": "C:\\laragon\\www\\catatan\\vendor\\codeigniter4\\framework\\system\\Cache\\CacheInterface.php", "source_location": "L43"}, {"id": "cache_cacheinterface_delete", "label": "delete()", "file_type": "code", "source_file": "C:\\laragon\\www\\catatan\\vendor\\codeigniter4\\framework\\system\\Cache\\CacheInterface.php", "source_location": "L52"}, {"id": "cache_cacheinterface_increment", "label": "increment()", "file_type": "code", "source_file": "C:\\laragon\\www\\catatan\\vendor\\codeigniter4\\framework\\system\\Cache\\CacheInterface.php", "source_location": "L62"}, {"id": "cache_cacheinterface_decrement", "label": "decrement()", "file_type": "code", "source_file": "C:\\laragon\\www\\catatan\\vendor\\codeigniter4\\framework\\system\\Cache\\CacheInterface.php", "source_location": "L72"}, {"id": "cache_cacheinterface_clean", "label": "clean()", "file_type": "code", "source_file": "C:\\laragon\\www\\catatan\\vendor\\codeigniter4\\framework\\system\\Cache\\CacheInterface.php", "source_location": "L79"}, {"id": "cache_cacheinterface_getcacheinfo", "label": "getCacheInfo()", "file_type": "code", "source_file": "C:\\laragon\\www\\catatan\\vendor\\codeigniter4\\framework\\system\\Cache\\CacheInterface.php", "source_location": "L89"}, {"id": "cache_cacheinterface_getmetadata", "label": "getMetaData()", "file_type": "code", "source_file": "C:\\laragon\\www\\catatan\\vendor\\codeigniter4\\framework\\system\\Cache\\CacheInterface.php", "source_location": "L100"}, {"id": "cache_cacheinterface_issupported", "label": "isSupported()", "file_type": "code", "source_file": "C:\\laragon\\www\\catatan\\vendor\\codeigniter4\\framework\\system\\Cache\\CacheInterface.php", "source_location": "L105"}], "edges": [{"source": "c_laragon_www_catatan_vendor_codeigniter4_framework_system_cache_cacheinterface_php", "target": "cache_cacheinterface_initialize", "relation": "contains", "confidence": "EXTRACTED", "source_file": "C:\\laragon\\www\\catatan\\vendor\\codeigniter4\\framework\\system\\Cache\\CacheInterface.php", "source_location": "L23", "weight": 1.0}, {"source": "c_laragon_www_catatan_vendor_codeigniter4_framework_system_cache_cacheinterface_php", "target": "cache_cacheinterface_get", "relation": "contains", "confidence": "EXTRACTED", "source_file": "C:\\laragon\\www\\catatan\\vendor\\codeigniter4\\framework\\system\\Cache\\CacheInterface.php", "source_location": "L32", "weight": 1.0}, {"source": "c_laragon_www_catatan_vendor_codeigniter4_framework_system_cache_cacheinterface_php", "target": "cache_cacheinterface_save", "relation": "contains", "confidence": "EXTRACTED", "source_file": "C:\\laragon\\www\\catatan\\vendor\\codeigniter4\\framework\\system\\Cache\\CacheInterface.php", "source_location": "L43", "weight": 1.0}, {"source": "c_laragon_www_catatan_vendor_codeigniter4_framework_system_cache_cacheinterface_php", "target": "cache_cacheinterface_delete", "relation": "contains", "confidence": "EXTRACTED", "source_file": "C:\\laragon\\www\\catatan\\vendor\\codeigniter4\\framework\\system\\Cache\\CacheInterface.php", "source_location": "L52", "weight": 1.0}, {"source": "c_laragon_www_catatan_vendor_codeigniter4_framework_system_cache_cacheinterface_php", "target": "cache_cacheinterface_increment", "relation": "contains", "confidence": "EXTRACTED", "source_file": "C:\\laragon\\www\\catatan\\vendor\\codeigniter4\\framework\\system\\Cache\\CacheInterface.php", "source_location": "L62", "weight": 1.0}, {"source": "c_laragon_www_catatan_vendor_codeigniter4_framework_system_cache_cacheinterface_php", "target": "cache_cacheinterface_decrement", "relation": "contains", "confidence": "EXTRACTED", "source_file": "C:\\laragon\\www\\catatan\\vendor\\codeigniter4\\framework\\system\\Cache\\CacheInterface.php", "source_location": "L72", "weight": 1.0}, {"source": "c_laragon_www_catatan_vendor_codeigniter4_framework_system_cache_cacheinterface_php", "target": "cache_cacheinterface_clean", "relation": "contains", "confidence": "EXTRACTED", "source_file": "C:\\laragon\\www\\catatan\\vendor\\codeigniter4\\framework\\system\\Cache\\CacheInterface.php", "source_location": "L79", "weight": 1.0}, {"source": "c_laragon_www_catatan_vendor_codeigniter4_framework_system_cache_cacheinterface_php", "target": "cache_cacheinterface_getcacheinfo", "relation": "contains", "confidence": "EXTRACTED", "source_file": "C:\\laragon\\www\\catatan\\vendor\\codeigniter4\\framework\\system\\Cache\\CacheInterface.php", "source_location": "L89", "weight": 1.0}, {"source": "c_laragon_www_catatan_vendor_codeigniter4_framework_system_cache_cacheinterface_php", "target": "cache_cacheinterface_getmetadata", "relation": "contains", "confidence": "EXTRACTED", "source_file": "C:\\laragon\\www\\catatan\\vendor\\codeigniter4\\framework\\system\\Cache\\CacheInterface.php", "source_location": "L100", "weight": 1.0}, {"source": "c_laragon_www_catatan_vendor_codeigniter4_framework_system_cache_cacheinterface_php", "target": "cache_cacheinterface_issupported", "relation": "contains", "confidence": "EXTRACTED", "source_file": "C:\\laragon\\www\\catatan\\vendor\\codeigniter4\\framework\\system\\Cache\\CacheInterface.php", "source_location": "L105", "weight": 1.0}], "raw_calls": []}